{
    "info": {
        "id": "BXe9Gon41TU",
        "title": "The Sea Nymphs - Dog Eat Spine",
        "thumbnail": "https://i.ytimg.com/vi_webp/BXe9Gon41TU/maxresdefault.webp",
        "description": "R.I.P. Tim Smith. Trying to do my part in sending him far and wide.\n\nThis is from their 1992 self-titled album.\n\nTo support the band and others related to Cardiacs, you can buy the rest of their music here:\nhttps://alphabet-business-concern.bandcamp.com/",
        "channel_url": "https://www.youtube.com/channel/UCr9YFqikzUj4l4r6BbXIZmA",
        "duration": 171,
        "view_count": 3584,
        "categories": [
            "Music"
        ],
        "tags": [
            "cardiacs",
            "tim smith",
            "music",
            "post punk",
            "prog rock",
            "the sea nymphs",
            "sea nymphs",
            "classical music",
            "dog eat spine"
        ],
        "playable_in_embed": true,
        "album": null,
        "artists": null,
        "artist": null,
        "track": null,
        "release_date": null,
        "release_year": null,
        "channel": "xyyz",
        "timestamp": 1599347070,
        "creators": null,
        "creator": null,
        "filesize": 2853899,
        "aspect_ratio": null
    },
    "beats": [
        [
            0.44,
            3.0
        ],
        [
            0.94,
            4.0
        ],
        [
            1.42,
            1.0
        ],
        [
            1.88,
            2.0
        ],
        [
            2.36,
            3.0
        ],
        [
            2.84,
            4.0
        ],
        [
            3.28,
            1.0
        ],
        [
            3.78,
            2.0
        ],
        [
            4.24,
            3.0
        ],
        [
            4.72,
            4.0
        ],
        [
            5.18,
            1.0
        ],
        [
            5.66,
            2.0
        ],
        [
            6.12,
            3.0
        ],
        [
            6.58,
            4.0
        ],
        [
            7.02,
            1.0
        ],
        [
            7.48,
            2.0
        ],
        [
            7.94,
            3.0
        ],
        [
            8.42,
            4.0
        ],
        [
            8.9,
            1.0
        ],
        [
            9.36,
            2.0
        ],
        [
            9.82,
            3.0
        ],
        [
            10.28,
            4.0
        ],
        [
            10.72,
            1.0
        ],
        [
            11.2,
            2.0
        ],
        [
            11.64,
            3.0
        ],
        [
            12.1,
            4.0
        ],
        [
            12.56,
            1.0
        ],
        [
            13.04,
            2.0
        ],
        [
            13.48,
            3.0
        ],
        [
            13.94,
            4.0
        ],
        [
            14.4,
            1.0
        ],
        [
            14.84,
            2.0
        ],
        [
            15.3,
            3.0
        ],
        [
            15.76,
            4.0
        ],
        [
            16.22,
            1.0
        ],
        [
            16.72,
            2.0
        ],
        [
            17.18,
            3.0
        ],
        [
            17.66,
            4.0
        ],
        [
            18.12,
            1.0
        ],
        [
            18.58,
            2.0
        ],
        [
            19.06,
            3.0
        ],
        [
            19.52,
            4.0
        ],
        [
            19.98,
            1.0
        ],
        [
            20.44,
            2.0
        ],
        [
            20.9,
            3.0
        ],
        [
            21.38,
            4.0
        ],
        [
            21.86,
            1.0
        ],
        [
            22.3,
            2.0
        ],
        [
            22.78,
            3.0
        ],
        [
            23.24,
            4.0
        ],
        [
            23.72,
            1.0
        ],
        [
            24.2,
            2.0
        ],
        [
            24.66,
            3.0
        ],
        [
            25.12,
            4.0
        ],
        [
            25.58,
            1.0
        ],
        [
            26.06,
            2.0
        ],
        [
            26.52,
            3.0
        ],
        [
            26.98,
            4.0
        ],
        [
            27.44,
            1.0
        ],
        [
            27.9,
            2.0
        ],
        [
            28.38,
            3.0
        ],
        [
            28.86,
            4.0
        ],
        [
            29.32,
            1.0
        ],
        [
            29.78,
            2.0
        ],
        [
            30.26,
            3.0
        ],
        [
            30.72,
            4.0
        ],
        [
            31.18,
            1.0
        ],
        [
            31.64,
            2.0
        ],
        [
            32.08,
            3.0
        ],
        [
            32.56,
            4.0
        ],
        [
            33.0,
            1.0
        ],
        [
            33.48,
            2.0
        ],
        [
            33.94,
            3.0
        ],
        [
            34.4,
            4.0
        ],
        [
            34.86,
            1.0
        ],
        [
            35.32,
            2.0
        ],
        [
            35.78,
            3.0
        ],
        [
            36.24,
            4.0
        ],
        [
            36.7,
            1.0
        ],
        [
            37.16,
            2.0
        ],
        [
            37.62,
            3.0
        ],
        [
            38.08,
            4.0
        ],
        [
            38.54,
            1.0
        ],
        [
            39.02,
            2.0
        ],
        [
            39.5,
            3.0
        ],
        [
            39.96,
            4.0
        ],
        [
            40.4,
            1.0
        ],
        [
            40.86,
            2.0
        ],
        [
            41.32,
            3.0
        ],
        [
            41.78,
            4.0
        ],
        [
            42.28,
            1.0
        ],
        [
            42.72,
            2.0
        ],
        [
            43.2,
            3.0
        ],
        [
            43.66,
            4.0
        ],
        [
            44.12,
            1.0
        ],
        [
            44.58,
            2.0
        ],
        [
            45.04,
            3.0
        ],
        [
            45.5,
            4.0
        ],
        [
            45.96,
            1.0
        ],
        [
            46.42,
            2.0
        ],
        [
            46.86,
            3.0
        ],
        [
            47.34,
            4.0
        ],
        [
            47.78,
            1.0
        ],
        [
            48.26,
            2.0
        ],
        [
            48.72,
            3.0
        ],
        [
            49.2,
            4.0
        ],
        [
            49.66,
            1.0
        ],
        [
            50.14,
            2.0
        ],
        [
            50.6,
            3.0
        ],
        [
            51.06,
            4.0
        ],
        [
            51.52,
            1.0
        ],
        [
            51.96,
            2.0
        ],
        [
            52.42,
            3.0
        ],
        [
            52.88,
            4.0
        ],
        [
            53.3,
            1.0
        ],
        [
            53.68,
            2.0
        ],
        [
            54.06,
            3.0
        ],
        [
            54.42,
            4.0
        ],
        [
            54.8,
            1.0
        ],
        [
            55.2,
            2.0
        ],
        [
            55.58,
            3.0
        ],
        [
            55.94,
            4.0
        ],
        [
            56.34,
            1.0
        ],
        [
            56.7,
            2.0
        ],
        [
            57.08,
            3.0
        ],
        [
            57.46,
            4.0
        ],
        [
            57.88,
            1.0
        ],
        [
            58.34,
            2.0
        ],
        [
            58.78,
            3.0
        ],
        [
            59.22,
            4.0
        ],
        [
            59.66,
            1.0
        ],
        [
            60.08,
            2.0
        ],
        [
            60.54,
            3.0
        ],
        [
            60.96,
            4.0
        ],
        [
            61.4,
            1.0
        ],
        [
            61.86,
            2.0
        ],
        [
            62.3,
            3.0
        ],
        [
            62.76,
            4.0
        ],
        [
            63.22,
            1.0
        ],
        [
            63.66,
            2.0
        ],
        [
            64.12,
            3.0
        ],
        [
            64.56,
            4.0
        ],
        [
            65.0,
            1.0
        ],
        [
            65.44,
            2.0
        ],
        [
            65.9,
            3.0
        ],
        [
            66.36,
            4.0
        ],
        [
            66.8,
            1.0
        ],
        [
            67.26,
            2.0
        ],
        [
            67.7,
            3.0
        ],
        [
            68.12,
            4.0
        ],
        [
            68.58,
            1.0
        ],
        [
            69.02,
            2.0
        ],
        [
            69.46,
            3.0
        ],
        [
            69.88,
            4.0
        ],
        [
            70.34,
            1.0
        ],
        [
            70.78,
            2.0
        ],
        [
            71.2,
            3.0
        ],
        [
            71.66,
            4.0
        ],
        [
            72.08,
            1.0
        ],
        [
            72.52,
            2.0
        ],
        [
            72.98,
            3.0
        ],
        [
            73.42,
            4.0
        ],
        [
            73.84,
            1.0
        ],
        [
            74.26,
            2.0
        ],
        [
            74.7,
            3.0
        ],
        [
            75.14,
            4.0
        ],
        [
            75.58,
            1.0
        ],
        [
            76.02,
            2.0
        ],
        [
            76.46,
            3.0
        ],
        [
            76.9,
            4.0
        ],
        [
            77.32,
            1.0
        ],
        [
            77.76,
            2.0
        ],
        [
            78.22,
            3.0
        ],
        [
            78.68,
            4.0
        ],
        [
            79.12,
            1.0
        ],
        [
            79.6,
            2.0
        ],
        [
            80.04,
            3.0
        ],
        [
            80.52,
            4.0
        ],
        [
            80.98,
            1.0
        ],
        [
            81.42,
            2.0
        ],
        [
            81.88,
            3.0
        ],
        [
            82.34,
            4.0
        ],
        [
            82.78,
            1.0
        ],
        [
            83.26,
            2.0
        ],
        [
            83.7,
            3.0
        ],
        [
            84.16,
            4.0
        ],
        [
            84.62,
            1.0
        ],
        [
            85.08,
            2.0
        ],
        [
            85.56,
            3.0
        ],
        [
            86.0,
            4.0
        ],
        [
            86.46,
            1.0
        ],
        [
            86.92,
            2.0
        ],
        [
            87.4,
            3.0
        ],
        [
            87.84,
            4.0
        ],
        [
            88.32,
            1.0
        ],
        [
            88.78,
            2.0
        ],
        [
            89.24,
            3.0
        ],
        [
            89.7,
            4.0
        ],
        [
            90.16,
            1.0
        ],
        [
            90.6,
            2.0
        ],
        [
            91.08,
            3.0
        ],
        [
            91.58,
            4.0
        ],
        [
            92.02,
            1.0
        ],
        [
            92.48,
            2.0
        ],
        [
            92.96,
            3.0
        ],
        [
            93.42,
            4.0
        ],
        [
            93.88,
            1.0
        ],
        [
            94.34,
            2.0
        ],
        [
            94.8,
            3.0
        ],
        [
            95.26,
            4.0
        ],
        [
            95.7,
            1.0
        ],
        [
            96.16,
            2.0
        ],
        [
            96.62,
            3.0
        ],
        [
            97.08,
            4.0
        ],
        [
            97.54,
            1.0
        ],
        [
            98.0,
            2.0
        ],
        [
            98.46,
            3.0
        ],
        [
            98.94,
            4.0
        ],
        [
            99.36,
            1.0
        ],
        [
            99.8,
            2.0
        ],
        [
            100.28,
            3.0
        ],
        [
            100.74,
            4.0
        ],
        [
            101.18,
            1.0
        ],
        [
            101.66,
            2.0
        ],
        [
            102.12,
            3.0
        ],
        [
            102.56,
            4.0
        ],
        [
            103.02,
            1.0
        ],
        [
            103.46,
            2.0
        ],
        [
            103.92,
            3.0
        ],
        [
            104.36,
            4.0
        ],
        [
            104.8,
            1.0
        ],
        [
            105.26,
            2.0
        ],
        [
            105.74,
            3.0
        ],
        [
            106.2,
            4.0
        ],
        [
            106.64,
            1.0
        ],
        [
            107.1,
            2.0
        ],
        [
            107.56,
            3.0
        ],
        [
            108.02,
            4.0
        ],
        [
            108.46,
            1.0
        ],
        [
            108.92,
            2.0
        ],
        [
            109.36,
            3.0
        ],
        [
            109.8,
            4.0
        ],
        [
            110.22,
            1.0
        ],
        [
            110.68,
            2.0
        ],
        [
            111.14,
            3.0
        ],
        [
            111.6,
            4.0
        ],
        [
            112.06,
            1.0
        ],
        [
            112.48,
            2.0
        ],
        [
            112.94,
            3.0
        ],
        [
            113.36,
            4.0
        ],
        [
            113.82,
            1.0
        ],
        [
            114.26,
            2.0
        ],
        [
            114.68,
            3.0
        ],
        [
            115.14,
            4.0
        ],
        [
            115.58,
            1.0
        ],
        [
            116.02,
            2.0
        ],
        [
            116.46,
            3.0
        ],
        [
            116.92,
            4.0
        ],
        [
            117.36,
            1.0
        ],
        [
            117.86,
            2.0
        ],
        [
            118.38,
            3.0
        ],
        [
            118.88,
            4.0
        ],
        [
            119.36,
            1.0
        ],
        [
            119.86,
            2.0
        ],
        [
            120.38,
            3.0
        ],
        [
            120.82,
            4.0
        ],
        [
            121.24,
            1.0
        ],
        [
            121.68,
            2.0
        ],
        [
            122.08,
            3.0
        ],
        [
            122.5,
            4.0
        ],
        [
            122.94,
            1.0
        ],
        [
            123.36,
            2.0
        ],
        [
            123.78,
            3.0
        ],
        [
            124.22,
            4.0
        ],
        [
            124.64,
            1.0
        ],
        [
            125.1,
            2.0
        ],
        [
            125.52,
            3.0
        ],
        [
            125.96,
            4.0
        ],
        [
            126.4,
            1.0
        ],
        [
            126.84,
            2.0
        ],
        [
            127.3,
            3.0
        ],
        [
            127.72,
            4.0
        ],
        [
            128.16,
            1.0
        ],
        [
            128.62,
            2.0
        ],
        [
            129.06,
            3.0
        ],
        [
            129.52,
            4.0
        ],
        [
            129.96,
            1.0
        ],
        [
            130.42,
            2.0
        ],
        [
            130.86,
            3.0
        ],
        [
            131.3,
            4.0
        ],
        [
            131.74,
            1.0
        ],
        [
            132.18,
            2.0
        ],
        [
            132.62,
            3.0
        ],
        [
            133.04,
            4.0
        ],
        [
            133.5,
            1.0
        ],
        [
            133.94,
            2.0
        ],
        [
            134.38,
            3.0
        ],
        [
            134.82,
            4.0
        ],
        [
            135.28,
            1.0
        ],
        [
            135.7,
            2.0
        ],
        [
            136.14,
            3.0
        ],
        [
            136.58,
            4.0
        ],
        [
            137.02,
            1.0
        ],
        [
            137.48,
            2.0
        ],
        [
            137.92,
            3.0
        ],
        [
            138.36,
            4.0
        ],
        [
            138.8,
            1.0
        ],
        [
            139.24,
            2.0
        ],
        [
            139.66,
            3.0
        ],
        [
            140.1,
            4.0
        ],
        [
            140.54,
            1.0
        ],
        [
            140.96,
            2.0
        ],
        [
            141.42,
            3.0
        ],
        [
            141.84,
            4.0
        ],
        [
            142.28,
            1.0
        ],
        [
            142.72,
            2.0
        ],
        [
            143.16,
            3.0
        ],
        [
            143.58,
            4.0
        ],
        [
            144.04,
            1.0
        ],
        [
            144.48,
            2.0
        ],
        [
            144.9,
            3.0
        ],
        [
            145.34,
            4.0
        ],
        [
            145.76,
            1.0
        ],
        [
            146.2,
            2.0
        ],
        [
            146.64,
            3.0
        ],
        [
            147.06,
            4.0
        ],
        [
            147.5,
            1.0
        ],
        [
            147.94,
            2.0
        ],
        [
            148.38,
            3.0
        ],
        [
            148.82,
            4.0
        ],
        [
            149.24,
            1.0
        ],
        [
            149.68,
            2.0
        ],
        [
            150.1,
            3.0
        ],
        [
            150.52,
            4.0
        ],
        [
            150.96,
            1.0
        ],
        [
            151.42,
            2.0
        ],
        [
            151.84,
            3.0
        ],
        [
            152.24,
            4.0
        ],
        [
            152.68,
            1.0
        ],
        [
            153.12,
            2.0
        ],
        [
            153.58,
            3.0
        ],
        [
            154.02,
            4.0
        ],
        [
            154.44,
            1.0
        ],
        [
            154.9,
            2.0
        ],
        [
            155.32,
            3.0
        ],
        [
            155.78,
            4.0
        ],
        [
            156.28,
            1.0
        ],
        [
            156.78,
            2.0
        ],
        [
            157.28,
            3.0
        ],
        [
            157.78,
            4.0
        ],
        [
            158.28,
            1.0
        ],
        [
            158.78,
            2.0
        ],
        [
            159.28,
            3.0
        ],
        [
            159.78,
            4.0
        ],
        [
            160.28,
            1.0
        ],
        [
            160.78,
            2.0
        ],
        [
            161.26,
            3.0
        ],
        [
            161.76,
            4.0
        ],
        [
            162.26,
            1.0
        ],
        [
            162.76,
            2.0
        ],
        [
            163.28,
            3.0
        ],
        [
            163.76,
            4.0
        ],
        [
            164.26,
            1.0
        ],
        [
            164.76,
            2.0
        ],
        [
            165.26,
            3.0
        ]
    ],
    "chords": [
        [
            0.0,
            1.5325170068027212,
            "G:maj"
        ],
        [
            1.5325170068027212,
            1.9969160997732427,
            "Gb:maj"
        ],
        [
            1.9969160997732427,
            4.2260317460317465,
            "N"
        ],
        [
            4.2260317460317465,
            5.201269841269841,
            "G:maj"
        ],
        [
            5.201269841269841,
            5.944308390022676,
            "Gb:maj"
        ],
        [
            5.944308390022676,
            6.826666666666667,
            "F:maj"
        ],
        [
            6.826666666666667,
            7.430385487528345,
            "Bb:maj"
        ],
        [
            7.430385487528345,
            7.9412244897959186,
            "Eb:maj"
        ],
        [
            7.9412244897959186,
            9.05578231292517,
            "G:maj"
        ],
        [
            9.05578231292517,
            11.888616780045352,
            "N"
        ],
        [
            11.888616780045352,
            12.585215419501134,
            "G:maj"
        ],
        [
            12.585215419501134,
            13.14249433106576,
            "Gb:maj"
        ],
        [
            13.14249433106576,
            14.257052154195012,
            "F:maj"
        ],
        [
            14.257052154195012,
            15.185850340136055,
            "N"
        ],
        [
            15.185850340136055,
            16.300408163265306,
            "G:maj"
        ],
        [
            16.300408163265306,
            16.99700680272109,
            "F:maj"
        ],
        [
            16.99700680272109,
            17.832925170068027,
            "Bb:maj"
        ],
        [
            17.832925170068027,
            18.901043083900227,
            "C:maj"
        ],
        [
            18.901043083900227,
            21.594557823129254,
            "Bb:maj"
        ],
        [
            21.594557823129254,
            22.84843537414966,
            "G:min"
        ],
        [
            22.84843537414966,
            23.777233560090703,
            "F:maj"
        ],
        [
            23.777233560090703,
            24.52027210884354,
            "Bb:maj"
        ],
        [
            24.52027210884354,
            25.40263038548753,
            "C:maj"
        ],
        [
            25.40263038548753,
            26.33142857142857,
            "Bb:maj"
        ],
        [
            26.33142857142857,
            28.18902494331066,
            "N"
        ],
        [
            28.18902494331066,
            29.210702947845807,
            "G:maj"
        ],
        [
            29.210702947845807,
            29.72154195011338,
            "Gb:maj"
        ],
        [
            29.72154195011338,
            31.02185941043084,
            "F:maj"
        ],
        [
            31.02185941043084,
            31.579138321995465,
            "Bb:maj"
        ],
        [
            31.579138321995465,
            32.04353741496599,
            "Eb:maj"
        ],
        [
            32.04353741496599,
            32.92589569160998,
            "G:maj"
        ],
        [
            32.92589569160998,
            35.66585034013605,
            "N"
        ],
        [
            35.66585034013605,
            36.826848072562356,
            "G:maj"
        ],
        [
            36.826848072562356,
            37.47700680272109,
            "F:maj"
        ],
        [
            37.47700680272109,
            38.45224489795918,
            "Bb:maj"
        ],
        [
            38.45224489795918,
            39.288163265306125,
            "C:maj"
        ],
        [
            39.288163265306125,
            41.61015873015873,
            "Bb:maj"
        ],
        [
            41.61015873015873,
            42.21387755102041,
            "N"
        ],
        [
            42.21387755102041,
            43.0962358276644,
            "G:maj"
        ],
        [
            43.0962358276644,
            43.42131519274376,
            "C:min"
        ],
        [
            43.42131519274376,
            43.97859410430839,
            "F:maj"
        ],
        [
            43.97859410430839,
            44.95383219954648,
            "Bb:maj"
        ],
        [
            44.95383219954648,
            45.789750566893424,
            "C:maj"
        ],
        [
            45.789750566893424,
            46.95074829931973,
            "Bb:maj"
        ],
        [
            46.95074829931973,
            47.55446712018141,
            "F:maj"
        ],
        [
            47.55446712018141,
            48.6225850340136,
            "Bb:maj"
        ],
        [
            48.6225850340136,
            49.78358276643991,
            "A:maj"
        ],
        [
            49.78358276643991,
            51.40897959183673,
            "D:maj"
        ],
        [
            51.40897959183673,
            56.0065306122449,
            "A:maj"
        ],
        [
            56.0065306122449,
            61.765079365079366,
            "B:maj"
        ],
        [
            61.765079365079366,
            62.55455782312925,
            "E:maj"
        ],
        [
            62.55455782312925,
            63.297596371882086,
            "Gb:maj"
        ],
        [
            63.297596371882086,
            64.78367346938775,
            "G:maj"
        ],
        [
            64.78367346938775,
            66.03755102040816,
            "Gb:maj"
        ],
        [
            66.03755102040816,
            67.662947845805,
            "N"
        ],
        [
            67.662947845805,
            69.24190476190476,
            "D:maj"
        ],
        [
            69.24190476190476,
            70.35646258503401,
            "N"
        ],
        [
            70.35646258503401,
            71.3317006802721,
            "G:maj"
        ],
        [
            71.3317006802721,
            72.58557823129252,
            "N"
        ],
        [
            72.58557823129252,
            74.2574149659864,
            "C:min"
        ],
        [
            74.2574149659864,
            75.92925170068027,
            "N"
        ],
        [
            75.92925170068027,
            77.27600907029479,
            "C:min"
        ],
        [
            77.27600907029479,
            78.01904761904763,
            "G:maj"
        ],
        [
            78.01904761904763,
            78.90140589569161,
            "Gb:maj"
        ],
        [
            78.90140589569161,
            79.92308390022676,
            "F:maj"
        ],
        [
            79.92308390022676,
            80.38748299319728,
            "Bb:maj"
        ],
        [
            80.38748299319728,
            80.89832199546485,
            "Eb:maj"
        ],
        [
            80.89832199546485,
            81.68780045351474,
            "G:maj"
        ],
        [
            81.68780045351474,
            82.75591836734694,
            "Gb:maj"
        ],
        [
            82.75591836734694,
            83.49895691609977,
            "F:maj"
        ],
        [
            83.49895691609977,
            84.0562358276644,
            "Bb:maj"
        ],
        [
            84.0562358276644,
            84.47419501133787,
            "Eb:maj"
        ],
        [
            84.47419501133787,
            85.58875283446712,
            "G:maj"
        ],
        [
            85.58875283446712,
            86.37823129251701,
            "F:maj"
        ],
        [
            86.37823129251701,
            87.3534693877551,
            "Bb:maj"
        ],
        [
            87.3534693877551,
            88.18938775510205,
            "C:maj"
        ],
        [
            88.18938775510205,
            89.16462585034014,
            "Bb:maj"
        ],
        [
            89.16462585034014,
            90.00054421768708,
            "F:maj"
        ],
        [
            90.00054421768708,
            90.92934240362813,
            "Bb:maj"
        ],
        [
            90.92934240362813,
            92.18321995464852,
            "G:min"
        ],
        [
            92.18321995464852,
            92.83337868480726,
            "F:maj"
        ],
        [
            92.83337868480726,
            93.8550566893424,
            "Bb:maj"
        ],
        [
            93.8550566893424,
            94.64453514739229,
            "C:maj"
        ],
        [
            94.64453514739229,
            95.10893424036281,
            "Bb:maj"
        ],
        [
            95.10893424036281,
            97.47736961451247,
            "N"
        ],
        [
            97.47736961451247,
            104.72199546485261,
            "A:maj"
        ],
        [
            104.72199546485261,
            106.99755102040817,
            "B:maj"
        ],
        [
            106.99755102040817,
            107.60126984126984,
            "E:maj"
        ],
        [
            107.60126984126984,
            109.31954648526077,
            "B:maj"
        ],
        [
            109.31954648526077,
            111.36290249433107,
            "E:maj"
        ],
        [
            111.36290249433107,
            112.1059410430839,
            "Gb:maj"
        ],
        [
            112.1059410430839,
            112.94185941043084,
            "G:maj"
        ],
        [
            112.94185941043084,
            113.87065759637188,
            "F:maj"
        ],
        [
            113.87065759637188,
            114.89233560090703,
            "Gb:maj"
        ],
        [
            114.89233560090703,
            116.42485260770975,
            "N"
        ],
        [
            116.42485260770975,
            118.18956916099773,
            "D:maj"
        ],
        [
            118.18956916099773,
            118.88616780045352,
            "Bb:maj"
        ],
        [
            118.88616780045352,
            124.83047619047619,
            "N"
        ],
        [
            124.83047619047619,
            125.89859410430839,
            "Eb:maj"
        ],
        [
            125.89859410430839,
            126.68807256235829,
            "G:maj"
        ],
        [
            126.68807256235829,
            127.29179138321996,
            "Gb:maj"
        ],
        [
            127.29179138321996,
            128.4063492063492,
            "F:maj"
        ],
        [
            128.4063492063492,
            128.87074829931973,
            "Bb:maj"
        ],
        [
            128.87074829931973,
            129.42802721088435,
            "Eb:maj"
        ],
        [
            129.42802721088435,
            130.1710657596372,
            "G:maj"
        ],
        [
            130.1710657596372,
            130.77478458049887,
            "Gb:maj"
        ],
        [
            130.77478458049887,
            131.98222222222222,
            "F:maj"
        ],
        [
            131.98222222222222,
            132.44662131519274,
            "Bb:maj"
        ],
        [
            132.44662131519274,
            132.95746031746032,
            "Eb:maj"
        ],
        [
            132.95746031746032,
            134.16489795918366,
            "G:maj"
        ],
        [
            134.16489795918366,
            135.51165532879818,
            "F:maj"
        ],
        [
            135.51165532879818,
            136.02249433106576,
            "Bb:maj"
        ],
        [
            136.02249433106576,
            136.71909297052156,
            "Eb:maj"
        ],
        [
            136.71909297052156,
            137.22993197278913,
            "G:maj"
        ],
        [
            137.22993197278913,
            138.019410430839,
            "Gb:maj"
        ],
        [
            138.019410430839,
            139.04108843537415,
            "F:maj"
        ],
        [
            139.04108843537415,
            139.55192743764172,
            "Bb:maj"
        ],
        [
            139.55192743764172,
            140.01632653061225,
            "Eb:maj"
        ],
        [
            140.01632653061225,
            141.1308843537415,
            "G:maj"
        ],
        [
            141.1308843537415,
            143.49931972789116,
            "N"
        ],
        [
            143.49931972789116,
            144.66031746031746,
            "G:maj"
        ],
        [
            144.66031746031746,
            147.12163265306123,
            "N"
        ],
        [
            147.12163265306123,
            147.95755102040818,
            "G:maj"
        ],
        [
            147.95755102040818,
            148.6077097505669,
            "Gb:maj"
        ],
        [
            148.6077097505669,
            150.6510657596372,
            "N"
        ],
        [
            150.6510657596372,
            152.04426303854876,
            "G:maj"
        ],
        [
            152.04426303854876,
            153.94829931972788,
            "G:min"
        ],
        [
            153.94829931972788,
            154.55201814058958,
            "Ab:maj"
        ],
        [
            154.55201814058958,
            160.49632653061224,
            "N"
        ],
        [
            160.49632653061224,
            161.37868480725623,
            "Eb:maj"
        ],
        [
            161.37868480725623,
            164.722358276644,
            "G:maj"
        ],
        [
            164.722358276644,
            171.13106575963718,
            "N"
        ]
    ]
}